fugue_sql_antlr_cpp/__init__.py
fugue_sql_antlr_cpp/sa_fugue_sql_cpp_parser.cp38-win_amd64.pyd
fugue_sql_antlr_cpp/antlr4-cpp-runtime/ANTLRErrorListener.cpp
fugue_sql_antlr_cpp/antlr4-cpp-runtime/ANTLRErrorListener.h
fugue_sql_antlr_cpp/antlr4-cpp-runtime/ANTLRErrorStrategy.cpp
fugue_sql_antlr_cpp/antlr4-cpp-runtime/ANTLRErrorStrategy.h
fugue_sql_antlr_cpp/antlr4-cpp-runtime/ANTLRFileStream.cpp
fugue_sql_antlr_cpp/antlr4-cpp-runtime/ANTLRFileStream.h
fugue_sql_antlr_cpp/antlr4-cpp-runtime/ANTLRInputStream.cpp
fugue_sql_antlr_cpp/antlr4-cpp-runtime/ANTLRInputStream.h
fugue_sql_antlr_cpp/antlr4-cpp-runtime/BailErrorStrategy.cpp
fugue_sql_antlr_cpp/antlr4-cpp-runtime/BailErrorStrategy.h
fugue_sql_antlr_cpp/antlr4-cpp-runtime/BaseErrorListener.cpp
fugue_sql_antlr_cpp/antlr4-cpp-runtime/BaseErrorListener.h
fugue_sql_antlr_cpp/antlr4-cpp-runtime/BufferedTokenStream.cpp
fugue_sql_antlr_cpp/antlr4-cpp-runtime/BufferedTokenStream.h
fugue_sql_antlr_cpp/antlr4-cpp-runtime/CharStream.cpp
fugue_sql_antlr_cpp/antlr4-cpp-runtime/CharStream.h
fugue_sql_antlr_cpp/antlr4-cpp-runtime/CommonToken.cpp
fugue_sql_antlr_cpp/antlr4-cpp-runtime/CommonToken.h
fugue_sql_antlr_cpp/antlr4-cpp-runtime/CommonTokenFactory.cpp
fugue_sql_antlr_cpp/antlr4-cpp-runtime/CommonTokenFactory.h
fugue_sql_antlr_cpp/antlr4-cpp-runtime/CommonTokenStream.cpp
fugue_sql_antlr_cpp/antlr4-cpp-runtime/CommonTokenStream.h
fugue_sql_antlr_cpp/antlr4-cpp-runtime/ConsoleErrorListener.cpp
fugue_sql_antlr_cpp/antlr4-cpp-runtime/ConsoleErrorListener.h
fugue_sql_antlr_cpp/antlr4-cpp-runtime/DefaultErrorStrategy.cpp
fugue_sql_antlr_cpp/antlr4-cpp-runtime/DefaultErrorStrategy.h
fugue_sql_antlr_cpp/antlr4-cpp-runtime/DiagnosticErrorListener.cpp
fugue_sql_antlr_cpp/antlr4-cpp-runtime/DiagnosticErrorListener.h
fugue_sql_antlr_cpp/antlr4-cpp-runtime/Exceptions.cpp
fugue_sql_antlr_cpp/antlr4-cpp-runtime/Exceptions.h
fugue_sql_antlr_cpp/antlr4-cpp-runtime/FailedPredicateException.cpp
fugue_sql_antlr_cpp-0.2.2.dist-info/LICENSE
fugue_sql_antlr_cpp-0.2.2.dist-info/METADATA
fugue_sql_antlr_cpp-0.2.2.dist-info/WHEEL
fugue_sql_antlr_cpp-0.2.2.dist-info/top_level.txt
fugue_sql_antlr_cpp-0.2.2.dist-info/RECORD
