Metadata-Version: 2.1
Name: fugue-sql-antlr-cpp
Version: 0.2.2
Summary: Fugue SQL Antlr C++ Parser
Home-page: http://github.com/fugue-project/fugue
Author: The Fugue Development Team
Author-email: hello@fugue.ai
License: Apache-2.0
Keywords: distributed spark dask sql dsl domain specific language
Classifier: Development Status :: 3 - Alpha
Classifier: Intended Audience :: Developers
Classifier: Topic :: Software Development :: Libraries :: Python Modules
Classifier: License :: OSI Approved :: Apache Software License
Classifier: Programming Language :: Python :: 3
Classifier: Programming Language :: Python :: 3.8
Classifier: Programming Language :: Python :: 3.9
Classifier: Programming Language :: Python :: 3.10
Classifier: Programming Language :: Python :: 3.11
Classifier: Programming Language :: Python :: 3.12
Classifier: Programming Language :: Python :: 3 :: Only
Requires-Python: >=3.8
License-File: LICENSE
Requires-Dist: triad >=0.6.8
Requires-Dist: antlr4-python3-runtime <4.12
Requires-Dist: jinja2
Requires-Dist: packaging
